Metadata-Version: 1.1
Name: optrita
Version: 0.0.1
Summary: Optimization and Machine Learning from 0
Home-page: https://github.com/margaritageleta/optrita
Author: 3omni
Author-email: rita.geleta@jediupc.com
License: MIT
Download-URL: https://github.com/margaritageleta/optrita/archive/0.0.1.tar.gz
Keywords: python,optimization
Platform: UNKNOWN
Classifier: Development Status :: 3 - Alpha
Classifier: Intended Audience :: Developers
Classifier: Topic :: Software Development :: Build Tools
Classifier: License :: OSI Approved :: MIT License
Classifier: Programming Language :: Python :: 3
Classifier: Programming Language :: Python :: 3.4
Classifier: Programming Language :: Python :: 3.5
Classifier: Programming Language :: Python :: 3.6
Classifier: Programming Language :: Python :: 3.7
